jinja2_embedded/__init__.py
jinja2_embedded/loaders.py
jinja2_embedded-0.1.4.dist-info/METADATA
jinja2_embedded-0.1.4.dist-info/WHEEL
jinja2_embedded-0.1.4.dist-info/licenses/LICENSE
jinja2_embedded-0.1.4.dist-info/RECORD
