Metadata-Version: 2.3
Name: jinja2-embedded
Version: 0.1.4
Summary: Jinja2 template loader for embedded Python runtimes
Project-URL: Source, https://github.com/GPla/jinja2-embedded
Author-email: GPla <36087062+GPla@users.noreply.github.com>
License-Expression: MIT
License-File: LICENSE
Keywords: bundler,embedded,executable,jinja2,pyoxidizer,python
Classifier: Environment :: Web Environment
Classifier: Intended Audience :: Developers
Classifier: License :: OSI Approved :: MIT License
Classifier: Operating System :: OS Independent
Classifier: Programming Language :: Python :: 3.10
Classifier: Programming Language :: Python :: 3.11
Classifier: Programming Language :: Python :: 3.12
Classifier: Topic :: Internet :: WWW/HTTP :: Dynamic Content
Classifier: Topic :: Text Processing :: Markup :: HTML
Classifier: Typing :: Typed
Requires-Python: >=3.10
Requires-Dist: jinja2<4,>=3
Provides-Extra: tests
Requires-Dist: pyoxidizer>=0.24.0; extra == 'tests'
Requires-Dist: pytest-cov>=5.0.0; extra == 'tests'
Requires-Dist: pytest>=8.2.0; extra == 'tests'
